sb2sep/__init__.py
sb2sep/broadening_function_svd.py
sb2sep/calculate_radial_velocities.py
sb2sep/evaluate_ssr_results.py
sb2sep/gaussian_fitting.py
sb2sep/linear_limbd_coeff_estimate.py
sb2sep/rotational_broadening_function_fitting.py
sb2sep/spectral_separation_routine.py
sb2sep/spectrum_processing_functions.py
sb2sep/storage_classes.py
sb2sep-1.2.14.dist-info/LICENSE
sb2sep-1.2.14.dist-info/METADATA
sb2sep-1.2.14.dist-info/WHEEL
sb2sep-1.2.14.dist-info/top_level.txt
sb2sep-1.2.14.dist-info/RECORD
