Metadata-Version: 2.1
Name: sb2sep
Version: 1.2.14
Summary: Separate Stellar Component Spectra in SB2 Binary System
Home-page: https://github.com/jsinkbaek/sb2sep
Author-email: Jeppe Sinkbaek Thomsen <jeppest2@gmail.com>
Project-URL: Bug Tracker, https://github.com/jsinkbaek/sb2sep/issues
Keywords: SB2 binary analysis,astronomy,spectroscopy
Classifier: Programming Language :: Python :: 3
Classifier: Operating System :: OS Independent
Requires-Python: >=3.6
License-File: LICENSE
Requires-Dist: numpy (>=1.19.4)
Requires-Dist: scipy (>=1.5.4)
Requires-Dist: matplotlib (>=3.3.4)
Requires-Dist: lmfit (>=1.0.2)
Requires-Dist: joblib (>=0.17.0)
